catenets/__init__.py
catenets/logger.py
catenets/version.py
catenets/datasets/__init__.py
catenets/datasets/dataset_acic2016.py
catenets/datasets/dataset_ihdp.py
catenets/datasets/dataset_twins.py
catenets/datasets/network.py
catenets/experiment_utils/__init__.py
catenets/experiment_utils/base.py
catenets/experiment_utils/simulation_utils.py
catenets/experiment_utils/tester.py
catenets/experiment_utils/torch_metrics.py
catenets/models/__init__.py
catenets/models/constants.py
catenets/models/jax/__init__.py
catenets/models/jax/base.py
catenets/models/jax/disentangled_nets.py
catenets/models/jax/flextenet.py
catenets/models/jax/model_utils.py
catenets/models/jax/offsetnet.py
catenets/models/jax/pseudo_outcome_nets.py
catenets/models/jax/representation_nets.py
catenets/models/jax/rnet.py
catenets/models/jax/snet.py
catenets/models/jax/tnet.py
catenets/models/jax/transformation_utils.py
catenets/models/jax/xnet.py
catenets/models/torch/__init__.py
catenets/models/torch/base.py
catenets/models/torch/flextenet.py
catenets/models/torch/pseudo_outcome_nets.py
catenets/models/torch/representation_nets.py
catenets/models/torch/slearner.py
catenets/models/torch/snet.py
catenets/models/torch/tlearner.py
catenets/models/torch/utils/__init__.py
catenets/models/torch/utils/decorators.py
catenets/models/torch/utils/model_utils.py
catenets/models/torch/utils/transformations.py
catenets/models/torch/utils/weight_utils.py
docs/conf.py
experiments/__init__.py
experiments/experiments_AISTATS21/ihdp_experiments.py
experiments/experiments_AISTATS21/simulations_AISTATS.py
experiments/experiments_benchmarks_NeurIPS21/__init__.py
experiments/experiments_benchmarks_NeurIPS21/acic_experiments_catenets.py
experiments/experiments_benchmarks_NeurIPS21/ihdp_experiments_catenets.py
experiments/experiments_benchmarks_NeurIPS21/twins_experiments_catenets.py
experiments/experiments_inductivebias_NeurIPS21/__init__.py
experiments/experiments_inductivebias_NeurIPS21/experiments_AB.py
catenets-0.2.4.dist-info/LICENSE
catenets-0.2.4.dist-info/METADATA
catenets-0.2.4.dist-info/WHEEL
catenets-0.2.4.dist-info/top_level.txt
catenets-0.2.4.dist-info/RECORD
