Metadata-Version: 2.2
Name: catenets
Version: 0.2.4
Summary: Conditional Average Treatment Effect Estimation Using Neural Networks
Author: Alicia Curth
Author-email: amc253@cam.ac.uk
License: BSD-3-Clause
Platform: any
Classifier: Programming Language :: Python :: 3
Classifier: Topic :: Scientific/Engineering :: Artificial Intelligence
Classifier: Intended Audience :: Science/Research
Classifier: Operating System :: OS Independent
Requires-Python: >=3.9
License-File: LICENSE
Requires-Dist: gdown
Requires-Dist: jax>=0.3.16
Requires-Dist: jaxlib>=0.3.14; sys_platform != "win32"
Requires-Dist: loguru>=0.5.3
Requires-Dist: numpy>=1.20
Requires-Dist: pandas>=1.3; python_version >= "3.8"
Requires-Dist: pytest>=6.2.4
Requires-Dist: requests
Requires-Dist: scikit_learn>=0.24.2
Requires-Dist: scipy>=1.2
Requires-Dist: torch>=1.9
Provides-Extra: testing
Requires-Dist: bandit; extra == "testing"
Requires-Dist: black; extra == "testing"
Requires-Dist: catboost; extra == "testing"
Requires-Dist: flake8; extra == "testing"
Requires-Dist: pre-commit; extra == "testing"
Requires-Dist: pytest; extra == "testing"
Requires-Dist: xgboost; extra == "testing"
Requires-Dist: setuptools; extra == "testing"
Requires-Dist: pytest; extra == "testing"
Requires-Dist: pytest-cov; extra == "testing"
Requires-Dist: jupyter; extra == "testing"
Requires-Dist: notebook; extra == "testing"
Requires-Dist: py; extra == "testing"
